ros_rosidl_generator_py-0.24.2.data/data/lib/python3.13/site-packages/rosidl_generator_py/__init__.py
ros_rosidl_generator_py-0.24.2.data/data/lib/python3.13/site-packages/rosidl_generator_py/cli.py
ros_rosidl_generator_py-0.24.2.data/data/lib/python3.13/site-packages/rosidl_generator_py/generate_py_impl.py
ros_rosidl_generator_py-0.24.2.data/data/lib/python3.13/site-packages/rosidl_generator_py/import_type_support_impl.py
ros_rosidl_generator_py-0.24.2.data/data/lib/python3.13/site-packages/rosidl_generator_py/__pycache__/__init__.cpython-313.pyc
ros_rosidl_generator_py-0.24.2.data/data/lib/python3.13/site-packages/rosidl_generator_py/__pycache__/cli.cpython-313.pyc
ros_rosidl_generator_py-0.24.2.data/data/lib/python3.13/site-packages/rosidl_generator_py/__pycache__/generate_py_impl.cpython-313.pyc
ros_rosidl_generator_py-0.24.2.data/data/lib/python3.13/site-packages/rosidl_generator_py/__pycache__/import_type_support_impl.cpython-313.pyc
ros_rosidl_generator_py-0.24.2.data/data/lib/python3.13/site-packages/rosidl_generator_py-0.24.2-py3.13.egg-info/PKG-INFO
ros_rosidl_generator_py-0.24.2.data/data/lib/python3.13/site-packages/rosidl_generator_py-0.24.2-py3.13.egg-info/SOURCES.txt
ros_rosidl_generator_py-0.24.2.data/data/lib/python3.13/site-packages/rosidl_generator_py-0.24.2-py3.13.egg-info/dependency_links.txt
ros_rosidl_generator_py-0.24.2.data/data/lib/python3.13/site-packages/rosidl_generator_py-0.24.2-py3.13.egg-info/entry_points.txt
ros_rosidl_generator_py-0.24.2.data/data/lib/python3.13/site-packages/rosidl_generator_py-0.24.2-py3.13.egg-info/top_level.txt
ros_rosidl_generator_py-0.24.2.data/data/lib/rosidl_generator_py/rosidl_generator_py
ros_rosidl_generator_py-0.24.2.data/data/share/ament_index/resource_index/package_run_dependencies/rosidl_generator_py
ros_rosidl_generator_py-0.24.2.data/data/share/ament_index/resource_index/packages/rosidl_generator_py
ros_rosidl_generator_py-0.24.2.data/data/share/ament_index/resource_index/parent_prefix_path/rosidl_generator_py
ros_rosidl_generator_py-0.24.2.data/data/share/ament_index/resource_index/rosidl_generator_packages/rosidl_generator_py
ros_rosidl_generator_py-0.24.2.data/data/share/rosidl_generator_py/local_setup.bash
ros_rosidl_generator_py-0.24.2.data/data/share/rosidl_generator_py/local_setup.dsv
ros_rosidl_generator_py-0.24.2.data/data/share/rosidl_generator_py/local_setup.sh
ros_rosidl_generator_py-0.24.2.data/data/share/rosidl_generator_py/local_setup.zsh
ros_rosidl_generator_py-0.24.2.data/data/share/rosidl_generator_py/package.dsv
ros_rosidl_generator_py-0.24.2.dist-info/METADATA
ros_rosidl_generator_py-0.24.2.dist-info/WHEEL
ros_rosidl_generator_py-0.24.2.dist-info/entry_points.txt
ros_rosidl_generator_py-0.24.2.dist-info/top_level.txt
ros_rosidl_generator_py-0.24.2.dist-info/RECORD
